Metadata-Version: 2.0
Name: django-rest-coreapi-schema
Version: 0.1.2
Summary: Django restframework custom schema
Home-page: https://github.com/emilioag/django_rest_coreapi_schema
Author: The Python Packaging Authority
Author-email: agonzalez.emilio@gmail.com
License: UNKNOWN
Keywords: django restframework schema coreapi swagger
Platform: UNKNOWN
Classifier: Development Status :: 3 - Alpha
Classifier: Intended Audience :: Developers
Classifier: Topic :: Software Development :: Documentation
Classifier: License :: OSI Approved :: MIT License
Classifier: Programming Language :: Python :: 3.6
Requires-Dist: Django (==2.0)
Requires-Dist: Markdown (==2.6.10)
Requires-Dist: Pygments (==2.2.0)
Requires-Dist: coreapi (==2.3.3)
Requires-Dist: djangorestframework (==3.7.7)
Provides-Extra: dev
Requires-Dist: check-manifest; extra == 'dev'
Provides-Extra: test
Requires-Dist: coverage; extra == 'test'
